{"d":[{"__type":"Nettpositive.BureauOne.BusinessObjects.StateEntity","ItemId":1,"ItemDesc":"Andaman \u0026 Nicobar Islands","EquifaxCode":"AN","CibilCode":"35","ExperianCode":"35","HighmarkCode":"AN"},{"__type":"Nettpositive.BureauOne.BusinessObjects.StateEntity","ItemId":2,"ItemDesc":"Andhra Pradesh","EquifaxCode":"AP","CibilCode":"28","ExperianCode":"28","HighmarkCode":"AP"},{"__type":"Nettpositive.BureauOne.BusinessObjects.StateEntity","ItemId":3,"ItemDesc":"Arunachal Pradesh","EquifaxCode":"AR","CibilCode":"12","ExperianCode":"12","HighmarkCode":"AR"},{"__type":"Nettpositive.BureauOne.BusinessObjects.StateEntity","ItemId":4,"ItemDesc":"Assam","EquifaxCode":"AS","CibilCode":"18","ExperianCode":"18","HighmarkCode":"AS"},{"__type":"Nettpositive.BureauOne.BusinessObjects.StateEntity","ItemId":5,"ItemDesc":"Bihar","EquifaxCode":"BR","CibilCode":"10","ExperianCode":"10","HighmarkCode":"BR"},{"__type":"Nettpositive.BureauOne.BusinessObjects.StateEntity","ItemId":6,"ItemDesc":"Chandigarh","EquifaxCode":"CH","CibilCode":"04","ExperianCode":"04","HighmarkCode":"CH"},{"__type":"Nettpositive.BureauOne.BusinessObjects.StateEntity","ItemId":7,"ItemDesc":"Chattisgarh","EquifaxCode":"CG","CibilCode":"22","ExperianCode":"22","HighmarkCode":"CG"},{"__type":"Nettpositive.BureauOne.BusinessObjects.StateEntity","ItemId":8,"ItemDesc":"Dadra and Nagar Haveli","EquifaxCode":"DN","CibilCode":"26","ExperianCode":"26","HighmarkCode":"DN"},{"__type":"Nettpositive.BureauOne.BusinessObjects.StateEntity","ItemId":9,"ItemDesc":"Daman \u0026 Diu","EquifaxCode":"DD","CibilCode":"25","ExperianCode":"25","HighmarkCode":"DD"},{"__type":"Nettpositive.BureauOne.BusinessObjects.StateEntity","ItemId":10,"ItemDesc":"Delhi","EquifaxCode":"DL","CibilCode":"07","ExperianCode":"07","HighmarkCode":"DL"},{"__type":"Nettpositive.BureauOne.BusinessObjects.StateEntity","ItemId":11,"ItemDesc":"Goa","EquifaxCode":"GA","CibilCode":"30","ExperianCode":"30","HighmarkCode":"GA"},{"__type":"Nettpositive.BureauOne.BusinessObjects.StateEntity","ItemId":12,"ItemDesc":"Gujarat","EquifaxCode":"GJ","CibilCode":"24","ExperianCode":"24","HighmarkCode":"GJ"},{"__type":"Nettpositive.BureauOne.BusinessObjects.StateEntity","ItemId":13,"ItemDesc":"Haryana","EquifaxCode":"HR","CibilCode":"06","ExperianCode":"06","HighmarkCode":"HR"},{"__type":"Nettpositive.BureauOne.BusinessObjects.StateEntity","ItemId":14,"ItemDesc":"Himachal Pradesh","EquifaxCode":"HP","CibilCode":"02","ExperianCode":"02","HighmarkCode":"HP"},{"__type":"Nettpositive.BureauOne.BusinessObjects.StateEntity","ItemId":15,"ItemDesc":"Jammu \u0026 Kashmir","EquifaxCode":"JK","CibilCode":"01","ExperianCode":"01","HighmarkCode":"JK"},{"__type":"Nettpositive.BureauOne.BusinessObjects.StateEntity","ItemId":16,"ItemDesc":"Jharkhand","EquifaxCode":"JH","CibilCode":"20","ExperianCode":"20","HighmarkCode":"JH"},{"__type":"Nettpositive.BureauOne.BusinessObjects.StateEntity","ItemId":17,"ItemDesc":"Karnataka","EquifaxCode":"KA","CibilCode":"29","ExperianCode":"29","HighmarkCode":"KA"},{"__type":"Nettpositive.BureauOne.BusinessObjects.StateEntity","ItemId":18,"ItemDesc":"Kerala","EquifaxCode":"KL","CibilCode":"32","ExperianCode":"32","HighmarkCode":"KL"},{"__type":"Nettpositive.BureauOne.BusinessObjects.StateEntity","ItemId":19,"ItemDesc":"Lakshadweep","EquifaxCode":"LD","CibilCode":"31","ExperianCode":"31","HighmarkCode":"LD"},{"__type":"Nettpositive.BureauOne.BusinessObjects.StateEntity","ItemId":20,"ItemDesc":"Madhya Pradesh","EquifaxCode":"MP","CibilCode":"23","ExperianCode":"23","HighmarkCode":"MP"},{"__type":"Nettpositive.BureauOne.BusinessObjects.StateEntity","ItemId":21,"ItemDesc":"Maharashtra","EquifaxCode":"MH","CibilCode":"27","ExperianCode":"27","HighmarkCode":"MH"},{"__type":"Nettpositive.BureauOne.BusinessObjects.StateEntity","ItemId":22,"ItemDesc":"Manipur","EquifaxCode":"MN","CibilCode":"14","ExperianCode":"14","HighmarkCode":"MN"},{"__type":"Nettpositive.BureauOne.BusinessObjects.StateEntity","ItemId":23,"ItemDesc":"Meghalaya","EquifaxCode":"ML","CibilCode":"17","ExperianCode":"17","HighmarkCode":"ML"},{"__type":"Nettpositive.BureauOne.BusinessObjects.StateEntity","ItemId":24,"ItemDesc":"Mizoram","EquifaxCode":"MZ","CibilCode":"15","ExperianCode":"15","HighmarkCode":"MZ"},{"__type":"Nettpositive.BureauOne.BusinessObjects.StateEntity","ItemId":25,"ItemDesc":"Nagaland","EquifaxCode":"NL","CibilCode":"13","ExperianCode":"13","HighmarkCode":"NL"},{"__type":"Nettpositive.BureauOne.BusinessObjects.StateEntity","ItemId":26,"ItemDesc":"Orissa","EquifaxCode":"OR","CibilCode":"21","ExperianCode":"21","HighmarkCode":"OR"},{"__type":"Nettpositive.BureauOne.BusinessObjects.StateEntity","ItemId":27,"ItemDesc":"Pondicherry/Puducherry","EquifaxCode":"PY","CibilCode":"34","ExperianCode":"34","HighmarkCode":"PY"},{"__type":"Nettpositive.BureauOne.BusinessObjects.StateEntity","ItemId":28,"ItemDesc":"Punjab","EquifaxCode":"PB","CibilCode":"03","ExperianCode":"03","HighmarkCode":"PB"},{"__type":"Nettpositive.BureauOne.BusinessObjects.StateEntity","ItemId":29,"ItemDesc":"Rajasthan","EquifaxCode":"RJ","CibilCode":"08","ExperianCode":"08","HighmarkCode":"RJ"},{"__type":"Nettpositive.BureauOne.BusinessObjects.StateEntity","ItemId":30,"ItemDesc":"Sikkim","EquifaxCode":"SK","CibilCode":"11","ExperianCode":"11","HighmarkCode":"SK"},{"__type":"Nettpositive.BureauOne.BusinessObjects.StateEntity","ItemId":31,"ItemDesc":"Tamil Nadu","EquifaxCode":"TN","CibilCode":"33","ExperianCode":"33","HighmarkCode":"TN"},{"__type":"Nettpositive.BureauOne.BusinessObjects.StateEntity","ItemId":32,"ItemDesc":"Tripura","EquifaxCode":"TR","CibilCode":"16","ExperianCode":"16","HighmarkCode":"TR"},{"__type":"Nettpositive.BureauOne.BusinessObjects.StateEntity","ItemId":33,"ItemDesc":"Uttar Pradesh","EquifaxCode":"UP","CibilCode":"09","ExperianCode":"09","HighmarkCode":"UP"},{"__type":"Nettpositive.BureauOne.BusinessObjects.StateEntity","ItemId":34,"ItemDesc":"Uttaranchal/Uttarakhand","EquifaxCode":"UL","CibilCode":"05","ExperianCode":"05","HighmarkCode":"UK"},{"__type":"Nettpositive.BureauOne.BusinessObjects.StateEntity","ItemId":35,"ItemDesc":"West Bengal","EquifaxCode":"WB","CibilCode":"19","ExperianCode":"19","HighmarkCode":"WB"}]}